mads/__init__.py
mads/agent_manager.py
mads/chat_manager.py
mads/config.py
pymads-0.0.6.dist-info/LICENSE
pymads-0.0.6.dist-info/METADATA
pymads-0.0.6.dist-info/WHEEL
pymads-0.0.6.dist-info/top_level.txt
pymads-0.0.6.dist-info/RECORD
