Metadata-Version: 2.1
Name: pymads
Version: 0.0.6
Summary: A framework that uses multi-agents to enable users to perform a systematic data science pipeline with just two inputs.
Author-email: Diogo Pedrosa <diogofranciscop@hotmail.com>, Iago Gaspar <wutsuperwut@gmail.com>
Project-URL: Homepage, https://github.com/AiFlowSolutions/MADS
Project-URL: Issues, https://github.com/AiFlowSolutions/MADS/issues
Classifier: Programming Language :: Python :: 3
Classifier: License :: OSI Approved :: MIT License
Classifier: Operating System :: OS Independent
Requires-Python: >=3.11.7
License-File: LICENSE
Requires-Dist: annotated-types >=0.7.0
Requires-Dist: anyio >=4.4.0
Requires-Dist: certifi >=2024.6.2
Requires-Dist: charset-normalizer >=3.3.2
Requires-Dist: colorama >=0.4.6
Requires-Dist: diskcache >=5.6.3
Requires-Dist: distro >=1.9.0
Requires-Dist: docker >=7.1.0
Requires-Dist: FLAML >=2.1.2
Requires-Dist: h11 >=0.14.0
Requires-Dist: httpcore >=1.0.5
Requires-Dist: httpx >=0.27.0
Requires-Dist: idna >=3.7
Requires-Dist: numpy >=1.26.4
Requires-Dist: openai >=1.31.0
Requires-Dist: packaging >=24.0
Requires-Dist: pandas >=2.2.2
Requires-Dist: pyautogen >=0.2.28
Requires-Dist: pydantic >=2.7.3
Requires-Dist: pydantic-core >=2.18.4
Requires-Dist: python-dateutil >=2.9.0.post0
Requires-Dist: python-dotenv >=1.0.1
Requires-Dist: pytz >=2024.1
Requires-Dist: regex >=2024.5.15
Requires-Dist: requests >=2.32.3
Requires-Dist: six >=1.16.0
Requires-Dist: sniffio >=1.3.1
Requires-Dist: termcolor >=2.4.0
Requires-Dist: tiktoken >=0.7.0
Requires-Dist: tqdm >=4.66.4
Requires-Dist: typing-extensions >=4.12.1
Requires-Dist: tzdata >=2024.1
Requires-Dist: urllib3 >=2.2.1
